aiszrhk/llm4data/__init__.py
aiszrhk/llm4data/utils.py
aiszrhk-0.1.14.dist-info/licenses/LICENSE
aiszrhk-0.1.14.dist-info/METADATA
aiszrhk-0.1.14.dist-info/WHEEL
aiszrhk-0.1.14.dist-info/top_level.txt
aiszrhk-0.1.14.dist-info/RECORD
