Metadata-Version: 2.4
Name: aiszrhk
Version: 0.1.14
Summary: A lightweight and customizable API wrapper designed to assist data analysts
Author-email: "Zhairui Shen(Laurent)" <century8613@gmail.com>
Maintainer-email: "Zhairui Shen(Laurent)" <admin@szr.hk>
License: MIT
Project-URL: Homepage, https://szr.hk
Project-URL: MyHomepage, https://szr.hk/me
Project-URL: Repository, https://github.com/LaurentShen
Project-URL: DOWNLOAD, https://pypi.org/project/aiszrhk/
Keywords: LLM,AI,ChatGPT,API,Data analysts
Requires-Python: >=3.7
License-File: LICENSE
Requires-Dist: requests
Requires-Dist: pandas
Requires-Dist: tiktoken
Requires-Dist: openai
Requires-Dist: InquirerPy
Requires-Dist: tqdm
Dynamic: license-file
